[
 {
  "hid":1,
  "sid":"rpi_camera_feed",
  "rsid":"rpi_camera_feed",
  "esid":"",
  "parent":0,
  "children":[
  ],
  "name":"rpi_camera_feed",
  "fullname":"rpi_camera_feed",
  "label":"rpi_camera_feed",
  "className":"Simulink.BlockDiagram",
  "icon":"SimulinkModelIcon_icon",
  "svg":"support/slwebview_files/rpi_camera_feed_d.svg",
  "thumbnail":"support/slwebview_files/rpi_camera_feed_d.png",
  "elements":[
   {
    "sid":"rpi_camera_feed:11",
    "rsid":"rpi_camera_feed:11",
    "name":"Atan2",
    "label":"Atan2",
    "className":"Simulink.Trigonometry",
    "icon":"BlockIcon_icon"
   },
   {
    "sid":"rpi_camera_feed:12",
    "rsid":"rpi_camera_feed:12",
    "name":"Constant",
    "label":"Constant",
    "className":"Simulink.Constant",
    "icon":"BlockIcon_icon"
   },
   {
    "sid":"rpi_camera_feed:13",
    "rsid":"rpi_camera_feed:13",
    "name":"Constant1",
    "label":"Constant1",
    "className":"Simulink.Constant",
    "icon":"BlockIcon_icon"
   },
   {
    "sid":"rpi_camera_feed:29",
    "rsid":"rpi_camera_feed:29",
    "name":"Constant2",
    "label":"Constant2",
    "className":"Simulink.Constant",
    "icon":"BlockIcon_icon"
   },
   {
    "sid":"rpi_camera_feed:43",
    "rsid":"rpi_camera_feed:43",
    "name":"Constant3",
    "label":"Constant3",
    "className":"Simulink.Constant",
    "icon":"BlockIcon_icon"
   },
   {
    "sid":"rpi_camera_feed:14",
    "rsid":"rpi_camera_feed:14",
    "name":"Demux",
    "label":"Demux",
    "className":"Simulink.Demux",
    "icon":"BlockIcon_icon"
   },
   {
    "sid":"rpi_camera_feed:15",
    "rsid":"rpi_camera_feed:15",
    "name":"LIS3MDL Magnetometer",
    "label":"LIS3MDL Magnetometer",
    "className":"Simulink.MATLABSystem",
    "icon":"BlockIcon_icon"
   },
   {
    "sid":"rpi_camera_feed:24",
    "rsid":"rpi_camera_feed:24",
    "name":"MATLAB Function",
    "label":"MATLAB Function",
    "className":"Simulink.SubSystem",
    "icon":"eml_icon"
   },
   {
    "sid":"rpi_camera_feed:8",
    "rsid":"rpi_camera_feed:8",
    "name":"Matrix\nConcatenate",
    "label":"Matrix Concatenate",
    "className":"Simulink.Concatenate",
    "icon":"BlockIcon_icon"
   },
   {
    "sid":"rpi_camera_feed:9",
    "rsid":"rpi_camera_feed:9",
    "name":"Permute\nDimensions",
    "label":"Permute Dimensions",
    "className":"Simulink.PermuteDimensions",
    "icon":"BlockIcon_icon"
   },
   {
    "sid":"rpi_camera_feed:16",
    "rsid":"rpi_camera_feed:16",
    "name":"Product",
    "label":"Product",
    "className":"Simulink.Product",
    "icon":"BlockIcon_icon"
   },
   {
    "sid":"rpi_camera_feed:44",
    "rsid":"rpi_camera_feed:44",
    "name":"Rate Transition",
    "label":"Rate Transition",
    "className":"Simulink.RateTransition",
    "icon":"BlockIcon_icon"
   },
   {
    "sid":"rpi_camera_feed:45",
    "rsid":"rpi_camera_feed:45",
    "name":"Rate Transition1",
    "label":"Rate Transition1",
    "className":"Simulink.RateTransition",
    "icon":"BlockIcon_icon"
   },
   {
    "sid":"rpi_camera_feed:46",
    "rsid":"rpi_camera_feed:46",
    "name":"Rate Transition2",
    "label":"Rate Transition2",
    "className":"Simulink.RateTransition",
    "icon":"BlockIcon_icon"
   },
   {
    "sid":"rpi_camera_feed:47",
    "rsid":"rpi_camera_feed:47",
    "name":"Rate Transition3",
    "label":"Rate Transition3",
    "className":"Simulink.RateTransition",
    "icon":"BlockIcon_icon"
   },
   {
    "sid":"rpi_camera_feed:48",
    "rsid":"rpi_camera_feed:48",
    "name":"Rate Transition4",
    "label":"Rate Transition4",
    "className":"Simulink.RateTransition",
    "icon":"BlockIcon_icon"
   },
   {
    "sid":"rpi_camera_feed:49",
    "rsid":"rpi_camera_feed:49",
    "name":"Rate Transition5",
    "label":"Rate Transition5",
    "className":"Simulink.RateTransition",
    "icon":"BlockIcon_icon"
   },
   {
    "sid":"rpi_camera_feed:50",
    "rsid":"rpi_camera_feed:50",
    "name":"Rate Transition6",
    "label":"Rate Transition6",
    "className":"Simulink.RateTransition",
    "icon":"BlockIcon_icon"
   },
   {
    "sid":"rpi_camera_feed:51",
    "rsid":"rpi_camera_feed:51",
    "name":"Rate Transition7",
    "label":"Rate Transition7",
    "className":"Simulink.RateTransition",
    "icon":"BlockIcon_icon"
   },
   {
    "sid":"rpi_camera_feed:34",
    "rsid":"rpi_camera_feed:34",
    "name":"Scope1",
    "label":"Scope1",
    "className":"Simulink.Scope",
    "icon":"BlockIcon_icon"
   },
   {
    "sid":"rpi_camera_feed:17",
    "rsid":"rpi_camera_feed:17",
    "name":"Sum",
    "label":"Sum",
    "className":"Simulink.Sum",
    "icon":"BlockIcon_icon"
   },
   {
    "sid":"rpi_camera_feed:36",
    "rsid":"rpi_camera_feed:36",
    "name":"Terminator1",
    "label":"Terminator1",
    "className":"Simulink.Terminator",
    "icon":"BlockIcon_icon"
   },
   {
    "sid":"rpi_camera_feed:37",
    "rsid":"rpi_camera_feed:37",
    "name":"Terminator2",
    "label":"Terminator2",
    "className":"Simulink.Terminator",
    "icon":"BlockIcon_icon"
   },
   {
    "sid":"rpi_camera_feed:23",
    "rsid":"rpi_camera_feed:23",
    "name":"To Workspace1",
    "label":"To Workspace1",
    "className":"Simulink.ToWorkspace",
    "icon":"BlockIcon_icon"
   },
   {
    "sid":"rpi_camera_feed:25",
    "rsid":"rpi_camera_feed:25",
    "name":"To Workspace2",
    "label":"To Workspace2",
    "className":"Simulink.ToWorkspace",
    "icon":"BlockIcon_icon"
   },
   {
    "sid":"rpi_camera_feed:28",
    "rsid":"rpi_camera_feed:28",
    "name":"To Workspace4",
    "label":"To Workspace4",
    "className":"Simulink.ToWorkspace",
    "icon":"BlockIcon_icon"
   },
   {
    "sid":"rpi_camera_feed:19",
    "rsid":"rpi_camera_feed:19",
    "name":"Unwrap",
    "label":"Unwrap",
    "className":"Simulink.SFunction",
    "icon":"BlockIcon_icon"
   },
   {
    "sid":"rpi_camera_feed:1",
    "rsid":"rpi_camera_feed:1",
    "name":"V4L2 Video Capture",
    "label":"V4L2 Video Capture",
    "className":"Simulink.MATLABSystem",
    "icon":"BlockIcon_icon"
   },
   {
    "sid":"rpi_camera_feed:35",
    "rsid":"rpi_camera_feed:35",
    "name":"XY Graph",
    "label":"XY Graph",
    "className":"Simulink.Record",
    "icon":"BlockIcon_icon"
   },
   {
    "sid":"rpi_camera_feed:1#out:1;line",
    "rsid":"rpi_camera_feed:1#out:1;line",
    "name":"",
    "label":"",
    "className":"Simulink.Line",
    "icon":"LineIcon_icon"
   },
   {
    "sid":"rpi_camera_feed:1#out:2;line",
    "rsid":"rpi_camera_feed:1#out:2;line",
    "name":"",
    "label":"",
    "className":"Simulink.Line",
    "icon":"LineIcon_icon"
   },
   {
    "sid":"rpi_camera_feed:1#out:3;line",
    "rsid":"rpi_camera_feed:1#out:3;line",
    "name":"",
    "label":"",
    "className":"Simulink.Line",
    "icon":"LineIcon_icon"
   },
   {
    "sid":"rpi_camera_feed:9#out:1;line",
    "rsid":"rpi_camera_feed:9#out:1;line",
    "name":"",
    "label":"",
    "className":"Simulink.Line",
    "icon":"LineIcon_icon"
   },
   {
    "sid":"rpi_camera_feed:14#out:1;line",
    "rsid":"rpi_camera_feed:14#out:1;line",
    "name":"",
    "label":"",
    "className":"Simulink.Line",
    "icon":"LineIcon_icon"
   },
   {
    "sid":"rpi_camera_feed:11#out:1;line",
    "rsid":"rpi_camera_feed:11#out:1;line",
    "name":"",
    "label":"",
    "className":"Simulink.Line",
    "icon":"LineIcon_icon"
   },
   {
    "sid":"rpi_camera_feed:12#out:1;line",
    "rsid":"rpi_camera_feed:12#out:1;line",
    "name":"",
    "label":"",
    "className":"Simulink.Line",
    "icon":"LineIcon_icon"
   },
   {
    "sid":"rpi_camera_feed:14#out:2;line",
    "rsid":"rpi_camera_feed:14#out:2;line",
    "name":"",
    "label":"",
    "className":"Simulink.Line",
    "icon":"LineIcon_icon"
   },
   {
    "sid":"rpi_camera_feed:17#out:1;line",
    "rsid":"rpi_camera_feed:17#out:1;line",
    "name":"",
    "label":"",
    "className":"Simulink.Line",
    "icon":"LineIcon_icon"
   },
   {
    "sid":"rpi_camera_feed:16#out:1;line",
    "rsid":"rpi_camera_feed:16#out:1;line",
    "name":"",
    "label":"",
    "className":"Simulink.Line",
    "icon":"LineIcon_icon"
   },
   {
    "sid":"rpi_camera_feed:50#out:1;line",
    "rsid":"rpi_camera_feed:50#out:1;line",
    "name":"",
    "label":"",
    "className":"Simulink.Line",
    "icon":"LineIcon_icon"
   },
   {
    "sid":"rpi_camera_feed:13#out:1;line",
    "rsid":"rpi_camera_feed:13#out:1;line",
    "name":"",
    "label":"",
    "className":"Simulink.Line",
    "icon":"LineIcon_icon"
   },
   {
    "sid":"rpi_camera_feed:29#out:1;line",
    "rsid":"rpi_camera_feed:29#out:1;line",
    "name":"",
    "label":"",
    "className":"Simulink.Line",
    "icon":"LineIcon_icon"
   },
   {
    "sid":"rpi_camera_feed:47#out:1;line",
    "rsid":"rpi_camera_feed:47#out:1;line",
    "name":"",
    "label":"",
    "className":"Simulink.Line",
    "icon":"LineIcon_icon"
   },
   {
    "sid":"rpi_camera_feed:8#out:1;line",
    "rsid":"rpi_camera_feed:8#out:1;line",
    "name":"",
    "label":"",
    "className":"Simulink.Line",
    "icon":"LineIcon_icon"
   },
   {
    "sid":"rpi_camera_feed:15#out:2;line",
    "rsid":"rpi_camera_feed:15#out:2;line",
    "name":"",
    "label":"",
    "className":"Simulink.Line",
    "icon":"LineIcon_icon"
   },
   {
    "sid":"rpi_camera_feed:15#out:3;line",
    "rsid":"rpi_camera_feed:15#out:3;line",
    "name":"",
    "label":"",
    "className":"Simulink.Line",
    "icon":"LineIcon_icon"
   },
   {
    "sid":"rpi_camera_feed:51#out:1;line",
    "rsid":"rpi_camera_feed:51#out:1;line",
    "name":"mag_heading",
    "label":"mag_heading",
    "className":"Simulink.Line",
    "icon":"LineIcon_icon"
   },
   {
    "sid":"rpi_camera_feed:48#out:1;line",
    "rsid":"rpi_camera_feed:48#out:1;line",
    "name":"error_est",
    "label":"error_est",
    "className":"Simulink.Line",
    "icon":"LineIcon_icon"
   },
   {
    "sid":"rpi_camera_feed:49#out:1;line",
    "rsid":"rpi_camera_feed:49#out:1;line",
    "name":"error_valid",
    "label":"error_valid",
    "className":"Simulink.Line",
    "icon":"LineIcon_icon"
   },
   {
    "sid":"rpi_camera_feed:43#out:1;line",
    "rsid":"rpi_camera_feed:43#out:1;line",
    "name":"",
    "label":"",
    "className":"Simulink.Line",
    "icon":"LineIcon_icon"
   },
   {
    "sid":"rpi_camera_feed:44#out:1;line",
    "rsid":"rpi_camera_feed:44#out:1;line",
    "name":"",
    "label":"",
    "className":"Simulink.Line",
    "icon":"LineIcon_icon"
   },
   {
    "sid":"rpi_camera_feed:45#out:1;line",
    "rsid":"rpi_camera_feed:45#out:1;line",
    "name":"",
    "label":"",
    "className":"Simulink.Line",
    "icon":"LineIcon_icon"
   },
   {
    "sid":"rpi_camera_feed:46#out:1;line",
    "rsid":"rpi_camera_feed:46#out:1;line",
    "name":"",
    "label":"",
    "className":"Simulink.Line",
    "icon":"LineIcon_icon"
   },
   {
    "sid":"rpi_camera_feed:24#out:1;line",
    "rsid":"rpi_camera_feed:24#out:1;line",
    "name":"",
    "label":"",
    "className":"Simulink.Line",
    "icon":"LineIcon_icon"
   },
   {
    "sid":"rpi_camera_feed:24#out:2;line",
    "rsid":"rpi_camera_feed:24#out:2;line",
    "name":"error_est",
    "label":"error_est",
    "className":"Simulink.Line",
    "icon":"LineIcon_icon"
   },
   {
    "sid":"rpi_camera_feed:24#out:3;line",
    "rsid":"rpi_camera_feed:24#out:3;line",
    "name":"error_valid",
    "label":"error_valid",
    "className":"Simulink.Line",
    "icon":"LineIcon_icon"
   },
   {
    "sid":"rpi_camera_feed:15#out:1;line",
    "rsid":"rpi_camera_feed:15#out:1;line",
    "name":"",
    "label":"",
    "className":"Simulink.Line",
    "icon":"LineIcon_icon"
   },
   {
    "sid":"rpi_camera_feed:19#out:1;line",
    "rsid":"rpi_camera_feed:19#out:1;line",
    "name":"mag_heading",
    "label":"mag_heading",
    "className":"Simulink.Line",
    "icon":"LineIcon_icon"
   }
  ],
  "sysViewURL":"support/slwebview_files/rpi_camera_feed_d.json",
  "sameAsElement":false
 }
]